{
  "listFolders": [
    {
      "name": "Math 200 Week 8",
      "listPages": [
        {
          "name": "Approximation",
          "listParagraphs": [
            {
              "text": "Tan plane, differential and linear approx. all related."
            }
            {
              "text": "tan plane of 3varfxn: fx(P)(x-a) + fy(P)(y-b) + fz(P)(z-c) = 0"
            }
          ],
          "listLinks": [
            {
              "Math 200 week 7"
            }
            {
              "Math 200 Midterm 2 review"
            }
          ]
        }
        {
          "name": "Gradient vectors and directional derivatives",
          "listParagraphs": [
            {
              "text": "gradient vectors are vectors whose components are the partial derivatives"
            }
          ],
          "listLinks": []
        }
      ]
    }
    {
      "name": "CO-OP INFORMATION",
      "listPages": []
    }
  ]
}